ARCHIVOS_VERILOG/GPIO_Single.v
module GPIO_Single (
    inout  wire PIN_DATA,          // Dato entrante o saliente desde o hacia el entorno
    input  wire clk,               // Señal de reloj
    input  wire reset,             // Señal de reinicio
    input  wire Enable,            // Habilitador del módulo (activo en bajo)
    input  wire Function,          // 0 = entrada, 1 = salida
    input  wire Data_out,          // Dato que se escribe hacia PIN_DATA
    input  wire Pin_Change_Mask,   // Habilita interrupción por cambio
    input  wire [1:0] Int_Mask,    // Tipo de interrupción
    output reg  Data_in,           // Datos leídos desde PIN_DATA
    output reg  Pin_out,           // Dato que se escribe al exterior si es salida
    output reg  IRQ_PIN_CHANGE,    // Señal de activación de cambio de pin
    output reg  IRQ_INT            // Señal de activación de interrupción
);

    // Registros internos
    reg PIN_DATA_prev;             // Almacena el valor previo de PIN_DATA para detectar flancos
    reg pin_direction;             // Registro para almacenar la dirección del pin
    reg pin_value;                 // Valor del pin para salida
    reg irq_detected;              // Señal interna de interrupción detectada
    reg enable_reg;                // Registro para almacenar el estado Enable
    reg function_reg;              // Registro para almacenar el estado Function
    reg pin_change_mask_reg;       // Registro para almacenar el estado Pin_Change_Mask
    reg [1:0] int_mask_reg;        // Registro para almacenar el estado Int_Mask
    
    // Controlar el pin bidireccional
    assign PIN_DATA = (enable_reg == 1'b0 && function_reg == 1'b1) ? pin_value : 1'bz;

//RST ASÍNCRONO
    always @(posedge clk or posedge reset) begin
        if (reset) begin
            // Reiniciar todos los registros
            Data_in <= 1'b0;
            Pin_out <= 1'b0;
            PIN_DATA_prev <= 1'b0;
            pin_direction <= 1'b0;  // Por defecto como entrada
            pin_value <= 1'b0;
            IRQ_PIN_CHANGE <= 1'b0;
            IRQ_INT <= 1'b0;
            irq_detected <= 1'b0;
            // Registros adicionales para guardar el estado de las señales de control
            enable_reg <= 1'b0;
            function_reg <= 1'b0;
            pin_change_mask_reg <= 1'b0;
            int_mask_reg <= 2'b00;
        end else begin
            // Actualizar registros de control
            enable_reg <= Enable;
            function_reg <= Function;
            pin_change_mask_reg <= Pin_Change_Mask;
            int_mask_reg <= Int_Mask;
            
            if (Enable == 1'b0) begin  // Módulo activo cuando Enable = 0
                // Actualizar la dirección del pin basado en Function
                pin_direction <= Function;
                
                // Gestionar modo entrada/salida
                if (Function == 1'b0) begin  // Modo entrada
                    Data_in <= PIN_DATA;     // Leer del pin externo
                    Pin_out <= 1'b0;         // Salida a 0 o alta impedancia
                end else begin              // Modo salida
                    pin_value <= Data_out;   // Escribir al pin externo
                    Pin_out <= Data_out;     // Actualizar también Pin_out
                end
                
                // Gestión de interrupciones (solo en modo entrada)
                if (Function == 1'b0 && pin_change_mask_reg) begin
                    // Detectar flancos
                    case (int_mask_reg)
                        2'b01: begin  // Flanco de subida
                            irq_detected <= (PIN_DATA == 1'b1 && PIN_DATA_prev == 1'b0);
                        end
                        2'b10: begin  // Flanco de bajada
                            irq_detected <= (PIN_DATA == 1'b0 && PIN_DATA_prev == 1'b1);
                        end
                        2'b11: begin  // Cualquier cambio
                            irq_detected <= (PIN_DATA != PIN_DATA_prev);
                        end
                        default: begin  // Interrupciones deshabilitadas
                            irq_detected <= 1'b0;
                        end
                    endcase
                    
                    // Generar pulsos de interrupción si se detecta un flanco
                    if (irq_detected) begin
                        IRQ_PIN_CHANGE <= 1'b1;
                        IRQ_INT <= 1'b1;
                        Data_in <= PIN_DATA;  // Actualizar Data_in con el valor actual del pin
                    end else begin
                        IRQ_PIN_CHANGE <= 1'b0;
                        IRQ_INT <= 1'b0;
                    end
                end else begin
                    IRQ_PIN_CHANGE <= 1'b0;
                    IRQ_INT <= 1'b0;
                    irq_detected <= 1'b0;
                end
                
                // Actualizar el valor previo para la próxima detección de flanco
                PIN_DATA_prev <= PIN_DATA;
            end else begin
                // Módulo inactivo (Enable = 1)
                // CORRECCIÓN: Reiniciar los valores cuando el módulo está deshabilitado
                Pin_out <= 1'b0;   // Resetear Pin_out cuando el módulo está deshabilitado
                IRQ_PIN_CHANGE <= 1'b0;
                IRQ_INT <= 1'b0;
                Data_in <= 1'b0;
            end
        end
    end

endmodule

ARCHIVOS_VERILOG/GPIO_Single_tb.v
`timescale 1ns / 1ps

module GPIO_Single_tb;

    // Señales para el módulo bajo prueba
    wire PIN_DATA;              // inout
    reg clk;                    // input
    reg reset;                  // input
    reg Enable;                 // input
    reg Function;               // input
    reg Data_out;               // input
    reg Pin_Change_Mask;        // input
    reg [1:0] Int_Mask;         // input
    wire Data_in;               // output
    wire Pin_out;               // output
    wire IRQ_PIN_CHANGE;        // output
    wire IRQ_INT;               // output
    
    // Para simular señales externas en el pin inout
    reg pin_external_driver;    // Para controlar el pin desde "fuera"
    reg pin_external_enable;    // Para habilitar el control externo

    // Asignación bidireccional para simular el entorno externo
    // Solo cuando el módulo no está en modo salida, para evitar conflictos
    assign PIN_DATA = pin_external_enable ? pin_external_driver : 1'bz;
    
    // Señal para monitoreo del PIN_DATA
    wire PIN_DATA_monitor = PIN_DATA;

    // Instancia del módulo bajo prueba
    GPIO_Single uut (
        .PIN_DATA(PIN_DATA),
        .clk(clk),
        .reset(reset),
        .Enable(Enable),
        .Function(Function),
        .Data_out(Data_out),
        .Pin_Change_Mask(Pin_Change_Mask),
        .Int_Mask(Int_Mask),
        .Data_in(Data_in),
        .Pin_out(Pin_out),
        .IRQ_PIN_CHANGE(IRQ_PIN_CHANGE),
        .IRQ_INT(IRQ_INT)
    );

    // Generación de reloj
    initial begin
        clk = 0;
        forever #5 clk = ~clk; // Reloj de 100MHz (periodo de 10ns)
    end

            // Generación de archivo VCD para gtkwave
    initial begin
        $dumpfile("gpio_single_tb.vcd");
        $dumpvars(0, GPIO_Single_tb);
        // Añadir explícitamente las señales internas para mejor visualización
        $dumpvars(0, uut.function_reg);
        $dumpvars(0, uut.enable_reg);
        $dumpvars(0, uut.pin_change_mask_reg);
        $dumpvars(0, uut.int_mask_reg);
        
        // Configuración inicial del banco de pruebas
        reset = 1;
        Enable = 0;         // Módulo activo
        Function = 0;       // Modo entrada
        Data_out = 0;
        Pin_Change_Mask = 0;
        Int_Mask = 2'b00;
        pin_external_driver = 0;
        pin_external_enable = 0;
        
        #20; // Esperar 20ns
        reset = 0; // Desactivar reset
        #10; // Esperar 10ns

        // Caso de prueba 1: Probar modo entrada (Function = 0)
        $display("Caso de prueba 1: Modo entrada (Function = 0)");
        Function = 0;       // Configurar como entrada
        pin_external_enable = 1; // Habilitar control externo
        #10;
        
        // Probar valores de entrada desde el exterior
        pin_external_driver = 1;
        #20;
        pin_external_driver = 0;
        #20;
        pin_external_driver = 1;
        #20;
        
        // Verificar que Data_in refleja PIN_DATA
        $display("PIN_DATA = %b, Data_in = %b (debería ser igual)", PIN_DATA, Data_in);
        
        // Caso de prueba 2: Probar modo salida (Function = 1)
        $display("Caso de prueba 2: Modo salida (Function = 1)");
        pin_external_enable = 0; // Deshabilitar control externo
        Function = 1;           // Configurar como salida
        #10;
        
        // Probar valores de salida
        Data_out = 0;
        #20;
        Data_out = 1;
        #20;
        Data_out = 0;
        #20;
        
        // Verificar que PIN_DATA y Pin_out reflejan Data_out
        $display("Data_out = %b, PIN_DATA = %b, Pin_out = %b (deberían ser iguales)", Data_out, PIN_DATA, Pin_out);
        
        // Caso de prueba 3: Probar Enable (desactivar módulo)
        $display("Caso de prueba 3: Desactivar módulo (Enable = 1)");
        Enable = 1;         // Desactivar módulo
        Data_out = 1;       // Cambiar salida
        #20;
        
        // Verificar que PIN_DATA está en alta impedancia (Z)
        $display("Enable = %b, PIN_DATA = %b (debería ser Z)", Enable, PIN_DATA);
        
        // Caso de prueba 4: Reactivar módulo
        $display("Caso de prueba 4: Reactivar módulo (Enable = 0)");
        Enable = 0;         // Reactivar módulo
        #20;
        
        // Verificar que PIN_DATA refleja Data_out nuevamente
        $display("Data_out = %b, PIN_DATA = %b (debería ser igual)", Data_out, PIN_DATA);
        
        // Caso de prueba 5: Probar interrupciones - Flanco de subida
        $display("Caso de prueba 5: Interrupción por flanco de subida");
        Function = 0;           // Modo entrada
        Pin_Change_Mask = 1;    // Activar interrupción
        Int_Mask = 2'b01;       // Flanco de subida
        pin_external_enable = 1; // Habilitar control externo
        pin_external_driver = 0; // Iniciar en 0
        #20;
        pin_external_driver = 1; // Cambiar a 1 (flanco de subida)
        #20;
        
        // Verificar interrupción
        $display("IRQ_PIN_CHANGE = %b, IRQ_INT = %b (deberían ser 1 durante un ciclo)", IRQ_PIN_CHANGE, IRQ_INT);
        
        pin_external_driver = 0; // Cambiar a 0 (no debería generar interrupción)
        #20;
        
        // Caso de prueba 6: Probar interrupciones - Flanco de bajada
        $display("Caso de prueba 6: Interrupción por flanco de bajada");
        Int_Mask = 2'b10;       // Flanco de bajada
        pin_external_driver = 1; // Iniciar en 1
        #20;
        pin_external_driver = 0; // Cambiar a 0 (flanco de bajada)
        #20;
        
        // Verificar interrupción
        $display("IRQ_PIN_CHANGE = %b, IRQ_INT = %b (deberían ser 1 durante un ciclo)", IRQ_PIN_CHANGE, IRQ_INT);
        
        // Caso de prueba 7: Probar interrupciones - Cualquier flanco
        $display("Caso de prueba 7: Interrupción por cualquier flanco");
        Int_Mask = 2'b11;       // Cualquier flanco
        #20;
        pin_external_driver = 1; // Cambiar a 1 (flanco de subida)
        #20;
        pin_external_driver = 0; // Cambiar a 0 (flanco de bajada)
        #20;
        
        // Verificar interrupciones
        $display("IRQ_PIN_CHANGE e IRQ_INT deberían activarse en ambos flancos");
        
        // Caso de prueba 8: Deshabilitar interrupciones
        $display("Caso de prueba 8: Deshabilitar interrupciones");
        Pin_Change_Mask = 0;    // Desactivar interrupciones
        
        // Primero, volver a modo entrada para permitir control externo
        Function = 0;
        #10;
        
        // Temporalmente deshabilitar la salida externa para el test
        // para evitar conflictos con el pin inout
        pin_external_enable = 0;
        #10;
        pin_external_enable = 1;
        pin_external_driver = 1; // Cambiar a 1
        #20;
        pin_external_driver = 0; // Cambiar a 0
        #20;
        pin_external_enable = 0; // Deshabilitar control externo
        
        // Verificar que no hay interrupciones
        $display("IRQ_PIN_CHANGE = %b, IRQ_INT = %b (deberían ser 0)", IRQ_PIN_CHANGE, IRQ_INT);
        
        // Caso de prueba 9: Probar interacción entre Function y interrupciones
        $display("Caso de prueba 9: Interacción entre Function y interrupciones");
        Pin_Change_Mask = 1;    // Activar interrupciones
        Int_Mask = 2'b11;       // Cualquier flanco
        Function = 1;           // Modo salida (no debería generar interrupciones)
        Data_out = 1;
        #20;
        Data_out = 0;
        #20;
        
        // Verificar que no hay interrupciones en modo salida
        $display("IRQ_PIN_CHANGE = %b, IRQ_INT = %b (deberían ser 0 en modo salida)", IRQ_PIN_CHANGE, IRQ_INT);
        
        // Caso de prueba 10: Probar Reset
        $display("Caso de prueba 10: Probar Reset");
        
        // Configurar algunas señales a valores distintos de cero
        Function = 1;
        Enable = 0;
        Pin_Change_Mask = 1;
        Int_Mask = 2'b11;
        Data_out = 1;
        #20;
        
        // Activar reset
        reset = 1;
        #20;
        
        // Verificar estado durante el reset
        $display("Durante reset: Function_reg=%b, Enable_reg=%b, Pin_Change_Mask_reg=%b, Int_Mask_reg=%b",
                 uut.function_reg, uut.enable_reg, uut.pin_change_mask_reg, uut.int_mask_reg);
        
        // Desactivar reset
        reset = 0;
        #20;
        
        // Verificar estado después del reset - todos los registros internos deben estar en 0
        $display("Después del reset, todos los registros internos deben estar en 0");
        $display("function_reg=%b, enable_reg=%b, pin_change_mask_reg=%b, int_mask_reg=%b",
                 uut.function_reg, uut.enable_reg, uut.pin_change_mask_reg, uut.int_mask_reg);
        
        // Finalizar simulación
        #100;
        $display("Test bench completado");
        $finish;
    end

endmodule

ARCHIVOS_VERILOG/gpio_single_tb.vcd
$date
	Wed May  7 06:45:22 2025
$end
$version
	Icarus Verilog
$end
$timescale
	1ps
$end
$scope module GPIO_Single_tb $end
$var wire 1 ! PIN_DATA $end
$var wire 1 " PIN_DATA_monitor $end
$var wire 1 # Pin_out $end
$var wire 1 $ IRQ_PIN_CHANGE $end
$var wire 1 % IRQ_INT $end
$var wire 1 & Data_in $end
$var reg 1 ' Data_out $end
$var reg 1 ( Enable $end
$var reg 1 ) Function $end
$var reg 2 * Int_Mask [1:0] $end
$var reg 1 + Pin_Change_Mask $end
$var reg 1 , clk $end
$var reg 1 - pin_external_driver $end
$var reg 1 . pin_external_enable $end
$var reg 1 / reset $end
$scope module uut $end
$var wire 1 ' Data_out $end
$var wire 1 ( Enable $end
$var wire 1 ) Function $end
$var wire 2 0 Int_Mask [1:0] $end
$var wire 1 ! PIN_DATA $end
$var wire 1 + Pin_Change_Mask $end
$var wire 1 , clk $end
$var wire 1 / reset $end
$var reg 1 & Data_in $end
$var reg 1 % IRQ_INT $end
$var reg 1 $ IRQ_PIN_CHANGE $end
$var reg 1 1 PIN_DATA_prev $end
$var reg 1 # Pin_out $end
$var reg 1 2 enable_reg $end
$var reg 1 3 function_reg $end
$var reg 2 4 int_mask_reg [1:0] $end
$var reg 1 5 irq_detected $end
$var reg 1 6 pin_change_mask_reg $end
$var reg 1 7 pin_direction $end
$var reg 1 8 pin_value $end
$upscope $end
$upscope $end
$enddefinitions $end
$comment Show the parameter values. $end
$dumpall
$end
#0
$dumpvars
08
07
06
05
b0 4
03
02
01
b0 0
1/
0.
0-
0,
0+
b0 *
0)
0(
0'
0&
0%
0$
0#
z"
z!
$end
#5000
1,
#10000
0,
#15000
1,
#20000
0,
0/
#25000
z1
z&
1,
#30000
0"
0!
0,
1.
#35000
01
0&
1,
#40000
1"
1!
0,
1-
#45000
11
1&
1,
#50000
0,
#55000
1,
#60000
0"
0!
0,
0-
#65000
01
0&
1,
#70000
0,
#75000
1,
#80000
1"
1!
0,
1-
#85000
11
1&
1,
#90000
0,
#95000
1,
#100000
z"
z!
0,
1)
0.
#105000
0"
0!
z1
17
13
1,
#110000
0,
#115000
01
1,
#120000
0,
#125000
1,
#130000
0,
1'
#135000
1"
1!
1#
18
1,
#140000
0,
#145000
11
1,
#150000
0,
0'
#155000
0"
0!
0#
08
1,
#160000
0,
#165000
01
1,
#170000
0,
1'
1(
#175000
z"
z!
12
1,
#180000
0,
#185000
1,
#190000
0,
0(
#195000
1"
1!
z1
1#
18
02
1,
#200000
0,
#205000
11
1,
#210000
x"
x!
0,
0-
1.
b1 *
b1 0
1+
0)
#215000
0"
0!
x1
0#
x&
07
b1 4
16
03
1,
#220000
0,
#225000
01
0&
1,
#230000
1"
1!
0,
1-
#235000
11
15
1&
1,
#240000
0,
#245000
1%
1$
05
1,
#250000
0"
0!
0,
0-
#255000
01
0%
0$
0&
1,
#260000
0,
#265000
1,
#270000
1"
1!
0,
1-
b10 *
b10 0
#275000
11
15
1&
b10 4
1,
#280000
0,
#285000
1%
1$
05
1,
#290000
0"
0!
0,
0-
#295000
01
0%
0$
15
0&
1,
#300000
0,
#305000
1%
1$
05
1,
#310000
0,
b11 *
b11 0
#315000
0%
0$
b11 4
1,
#320000
0,
#325000
1,
#330000
1"
1!
0,
1-
#335000
11
15
1&
1,
#340000
0,
#345000
1%
1$
05
1,
#350000
0"
0!
0,
0-
#355000
01
0%
0$
15
0&
1,
#360000
0,
#365000
1%
1$
05
1,
#370000
0,
0+
#375000
0%
0$
06
1,
#380000
z"
z!
0,
0.
#385000
z1
z&
1,
#390000
1"
1!
0,
1-
1.
#395000
11
1&
1,
#400000
0,
#405000
1,
#410000
0"
0!
0,
0-
#415000
01
0&
1,
#420000
0,
#425000
1,
#430000
z"
z!
0,
1)
1+
0.
#435000
1"
1!
z1
1#
17
16
13
1,
#440000
0,
#445000
11
1,
#450000
0,
0'
#455000
0"
0!
0#
08
1,
#460000
0,
#465000
01
1,
#470000
0,
1'
#475000
1"
1!
1#
18
1,
#480000
0,
#485000
11
1,
#490000
z"
z!
b0 4
06
03
08
07
01
0#
0,
1/
#495000
1,
#500000
0,
#505000
1,
#510000
0,
0/
#515000
1"
1!
z1
1#
18
17
b11 4
16
13
1,
#520000
0,
#525000
11
1,
